asciidoc_dita_toolkit/__init__.py
asciidoc_dita_toolkit/adt_core/__init__.py
asciidoc_dita_toolkit/adt_core/__main__.py
asciidoc_dita_toolkit/adt_core/cli.py
asciidoc_dita_toolkit/adt_core/exceptions.py
asciidoc_dita_toolkit/adt_core/module_sequencer.py
asciidoc_dita_toolkit/asciidoc_dita/__init__.py
asciidoc_dita_toolkit/asciidoc_dita/cli_utils.py
asciidoc_dita_toolkit/asciidoc_dita/config_utils.py
asciidoc_dita_toolkit/asciidoc_dita/file_utils.py
asciidoc_dita_toolkit/asciidoc_dita/plugin_manager.py
asciidoc_dita_toolkit/asciidoc_dita/regex_patterns.py
asciidoc_dita_toolkit/asciidoc_dita/security_utils.py
asciidoc_dita_toolkit/asciidoc_dita/user_interface.py
asciidoc_dita_toolkit/asciidoc_dita/workflow_utils.py
asciidoc_dita_toolkit/modules/__init__.py
asciidoc_dita_toolkit/modules/archive_unused_files/__init__.py
asciidoc_dita_toolkit/modules/content_type/__init__.py
asciidoc_dita_toolkit/modules/content_type/content_type_detector.py
asciidoc_dita_toolkit/modules/content_type/content_type_example_config.py
asciidoc_dita_toolkit/modules/content_type/content_type_processor.py
asciidoc_dita_toolkit/modules/content_type/ui_interface.py
asciidoc_dita_toolkit/modules/context_analyzer/__init__.py
asciidoc_dita_toolkit/modules/context_migrator/__init__.py
asciidoc_dita_toolkit/modules/cross_reference/__init__.py
asciidoc_dita_toolkit/modules/directory_config/__init__.py
asciidoc_dita_toolkit/modules/entity_reference/__init__.py
asciidoc_dita_toolkit/modules/example_block/__init__.py
asciidoc_dita_toolkit/modules/user_journey/__init__.py
asciidoc_dita_toolkit/modules/user_journey/userjourney_cli.py
asciidoc_dita_toolkit/modules/vale_flagger/__init__.py
asciidoc_dita_toolkit/plugins/__init__.py
asciidoc_dita_toolkit/plugins/vale_flagger/__init__.py
asciidoc_dita_toolkit/plugins/vale_flagger/cli.py
asciidoc_dita_toolkit/plugins/vale_flagger/config.py
asciidoc_dita_toolkit/plugins/vale_flagger/plugin.py
asciidoc_dita_toolkit/plugins/vale_flagger/vale_flagger.py
asciidoc_dita_toolkit-2.1.5.dist-info/licenses/LICENSE
asciidoc_dita_toolkit-2.1.5.dist-info/METADATA
asciidoc_dita_toolkit-2.1.5.dist-info/WHEEL
asciidoc_dita_toolkit-2.1.5.dist-info/entry_points.txt
asciidoc_dita_toolkit-2.1.5.dist-info/top_level.txt
asciidoc_dita_toolkit-2.1.5.dist-info/RECORD
