Metadata-Version: 2.4
Name: asciidoc-dita-toolkit
Version: 2.1.5
Summary: AsciiDoc DITA Toolkit - unified package for technical documentation workflows
Author-email: rolfedh <rolfedh@users.noreply.github.com>
Maintainer-email: rolfedh <rolfedh@users.noreply.github.com>
License-Expression: MIT
Project-URL: Homepage, https://github.com/rolfedh/asciidoc-dita-toolkit
Project-URL: Bug Reports, https://github.com/rolfedh/asciidoc-dita-toolkit/issues
Project-URL: Source, https://github.com/rolfedh/asciidoc-dita-toolkit
Project-URL: Documentation, https://github.com/rolfedh/asciidoc-dita-toolkit/blob/main/docs/
Keywords: asciidoc,dita,documentation,technical-writing,content-validation
Classifier: Development Status :: 4 - Beta
Classifier: Intended Audience :: Developers
Classifier: Intended Audience :: Information Technology
Classifier: Topic :: Documentation
Classifier: Topic :: Software Development :: Documentation
Classifier: Topic :: Text Processing :: Markup
Classifier: Programming Language :: Python :: 3
Classifier: Programming Language :: Python :: 3.8
Classifier: Programming Language :: Python :: 3.9
Classifier: Programming Language :: Python :: 3.10
Classifier: Programming Language :: Python :: 3.11
Classifier: Programming Language :: Python :: 3.12
Classifier: Operating System :: OS Independent
Requires-Python: >=3.8
License-File: LICENSE
Requires-Dist: importlib-metadata>=1.0; python_version < "3.8"
Requires-Dist: pyyaml>=5.1
Provides-Extra: dev
Requires-Dist: pytest>=6.0; extra == "dev"
Requires-Dist: pytest-cov>=2.0; extra == "dev"
Requires-Dist: black>=21.0; extra == "dev"
Requires-Dist: flake8>=3.8; extra == "dev"
Dynamic: license-file
